soh/__init__.py
soh/__version__.py
soh/b64.py
soh/cli.py
soh/create.py
soh/datetime.py
soh/epoch.py
soh/json.py
soh/secret.py
soh/serve.py
soh/system.py
soh/tokens.py
soh/util.py
soh/uuid.py
tests/__init__.py
tests/common.py
tests/conftest.py
tests/test_b64.py
tests/test_cli.py
tests/test_create.py
tests/test_datetime.py
tests/test_epoch.py
tests/test_json.py
tests/test_secret.py
tests/test_serve.py
tests/test_system.py
tests/test_tokens.py
tests/test_util.py
tests/test_uuid.py
soh-0.1.1.dist-info/LICENSE.txt
soh-0.1.1.dist-info/METADATA
soh-0.1.1.dist-info/WHEEL
soh-0.1.1.dist-info/entry_points.txt
soh-0.1.1.dist-info/top_level.txt
soh-0.1.1.dist-info/RECORD
