Metadata-Version: 2.1
Name: soh
Version: 0.1.1
Summary: Sleight of hand (soh) CLI tool.
Home-page: https://github.com/crflynn/soh
Author: Christopher Flynn
Author-email: crf204@gmail.com
License: MIT
Keywords: soh cli tool
Platform: UNKNOWN
Classifier: Development Status :: 4 - Beta
Classifier: License :: OSI Approved :: MIT License
Classifier: Topic :: Software Development :: Libraries :: Python Modules
Classifier: Programming Language :: Python
Classifier: Programming Language :: Python :: 3.7
Classifier: Programming Language :: Python :: Implementation :: CPython
Requires-Dist: arrow
Requires-Dist: click
Requires-Dist: pyperclip
Requires-Dist: requests
